Metadata-Version: 1.1
Name: pyrox
Version: 0.5.0
Summary: The high-speed HTTP middleware proxy for Python
Home-page: https://github.com/zinic/pyrox
Author: John Hopper
Author-email: john.hopper@jpserver.net
License: MIT
Platform: UNKNOWN
Classifier: Development Status :: 4 - Beta
Classifier: Environment :: Other Environment
Classifier: Natural Language :: English
Classifier: Intended Audience :: Developers
Classifier: License :: OSI Approved :: MIT License
Classifier: Programming Language :: Python
Classifier: Programming Language :: Cython
Classifier: Programming Language :: Python :: Implementation :: CPython
Classifier: Programming Language :: Python :: 2.7
Classifier: Programming Language :: Python :: 3.3
Classifier: Topic :: Internet
Classifier: Topic :: Utilities
